mcp_server_echo/__init__.py
baiyx_mcp_server_echo-0.1.3.dist-info/METADATA
baiyx_mcp_server_echo-0.1.3.dist-info/WHEEL
baiyx_mcp_server_echo-0.1.3.dist-info/entry_points.txt
baiyx_mcp_server_echo-0.1.3.dist-info/RECORD
