Metadata-Version: 2.4
Name: baiyx-mcp-server-echo
Version: 0.1.3
Summary: A Model Context Protocol server providing echo service for testing
Author-email: baiyx <baiyx@example.com>
License: MIT
Keywords: echo,llm,mcp
Classifier: Development Status :: 4 - Beta
Classifier: Intended Audience :: Developers
Classifier: License :: OSI Approved :: MIT License
Classifier: Programming Language :: Python :: 3
Classifier: Programming Language :: Python :: 3.10
Requires-Python: >=3.10
Requires-Dist: fastapi>=0.110.0
Requires-Dist: mcp>=1.0.0
Requires-Dist: pydantic>=2.0.0
Requires-Dist: uvicorn>=0.27.1
